halfadder.v
module  halfadder (
    a,b,c,sum
);
    input wire a,b;
    output wire c,sum;
    
    assign sum = a ^ b;
    assign c = a & b;
endmodule

fulladder_tb.v
`timescale 1ns/1ns 
module fulladder_tb;
    initial begin
        $dumpfile("test.vcd");
        $dumpvars(0,fulladder_tb);
    end

    reg a_tb,b_tb,c_in_tb;
    wire xor1_out,xor2_out,and1_out,and2_out,sum_tb,c_out_tb;

    halfadder halfadder1(
        .a(a_tb),
        .b(b_tb),
        .sum(xor1_out),
        .c(and1_out)
    );

    halfadder halfadder2(
        .a(xor1_out),
        .b(c_in_tb),
        .sum(xor2_out),
        .c(and2_out)
    );
    assign sum_tb = xor2_out;
    assign c_out = and1_out | and2_out;

    initial begin
        a_tb = 1'b0;
        b_tb = 1'b0;
        c_in_tb = 1'b0;
        #5
        a_tb = 1'b0;
        b_tb = 1'b1;
        c_in_tb = 1'b0;
        #5
        a_tb = 1'b1;
        b_tb = 1'b0;
        c_in_tb = 1'b0;
        #5
        a_tb = 1'b1;
        b_tb = 1'b1;
        c_in_tb = 1'b0;
        #5
        a_tb = 1'b0;
        b_tb = 1'b0;
        c_in_tb = 1'b1;
        #5
        a_tb = 1'b0;
        b_tb = 1'b1;
        c_in_tb = 1'b1;
        #5
        a_tb = 1'b1;
        b_tb = 1'b0;
        c_in_tb = 1'b1;
        #5
        a_tb = 1'b1;
        b_tb = 1'b1;
        c_in_tb = 1'b1;
        #40
       #40
       $finish;
    end
endmodule

test.vcd
$date
	Thu May  6 02:29:13 2021
$end
$version
	Icarus Verilog
$end
$timescale
	1ns
$end
$scope module fulladder_tb $end
$var wire 1 ! c_out $end
$var wire 1 " sum_tb $end
$var wire 1 # xor2_out $end
$var wire 1 $ xor1_out $end
$var wire 1 % and2_out $end
$var wire 1 & and1_out $end
$var reg 1 ' a_tb $end
$var reg 1 ( b_tb $end
$var reg 1 ) c_in_tb $end
$scope module halfadder1 $end
$var wire 1 ' a $end
$var wire 1 ( b $end
$var wire 1 & c $end
$var wire 1 $ sum $end
$upscope $end
$scope module halfadder2 $end
$var wire 1 $ a $end
$var wire 1 ) b $end
$var wire 1 % c $end
$var wire 1 # sum $end
$upscope $end
$upscope $end
$enddefinitions $end
#0
$dumpvars
0)
0(
0'
0&
0%
0$
0#
0"
0!
$end
#5
1"
1#
1$
1(
#10
0(
1'
#15
0"
0#
1!
0$
1&
1(
#20
0!
1"
1#
0&
1)
0(
0'
#25
1!
0"
0#
1%
1$
1(
#30
0(
1'
#35
1"
1#
0%
0$
1&
1(
